{
    "minimum_required": "v4.0",
    "opers": [
        {
            "name": "推进之王",
            "skill": 2,
            "skill_usage": 0
        },
        {
            "name": "伊芙利特",
            "skill": 2,
            "skill_usage": 0
        },
        {
            "name": "塞雷娅",
            "skill": 2,
            "skill_usage": 0
        }
    ],
    "actions": [
        {
            "location": [
                4,
                1
            ],
            "name": "推进之王",
            "type": "部署",
            "direction": "右"
        },
        {
            "location": [
                null,
                null
            ],
            "name": "",
            "type": "二倍速"
        },
        {
            "location": [
                6,
                1
            ],
            "type": "部署",
            "name": "塞雷娅",
            "direction": "左"
        },
        {
            "location": [
                5,
                5
            ],
            "type": "部署",
            "name": "伊芙利特",
            "direction": "上"
        }
    ],
    "doc": {
        "title": "https://www.bilibili.com/video/BV1KZ4y1v7gZ?p=7&share_source=copy_web"
    },
    "groups": [],
    "stage_name": "DV-6"
}