{
    "minimum_required": "v4.0.0",
    "stage_name": "act19mini_07",
    "actions": [
        {
            "type": "Deploy",
            "name": "桃金娘",
            "location": [
                8,
                6
            ],
            "direction": "Left"
        },
        {
            "type": "SpeedUp"
        },
        {
            "type": "Deploy",
            "location": [
                5,
                3
            ],
            "name": "乌尔比安",
            "direction": "Down"
        },
        {
            "type": "Deploy",
            "name": "苏苏洛/华法林",
            "direction": "Right",
            "location": [
                2,
                4
            ]
        },
        {
            "type": "Deploy",
            "name": "古米",
            "location": [
                7,
                6
            ],
            "direction": "Left"
        },
        {
            "type": "SkillUsage",
            "name": "桃金娘",
            "skill_usage": 2,
            "skill_times": 1
        },
        {
            "type": "SkillUsage",
            "name": "苏苏洛",
            "skill_usage": 2,
            "skill_times": 1
        },
        {
            "type": "Deploy",
            "name": "元素奶",
            "location": [
                8,
                5
            ],
            "direction": "Left"
        },
        {
            "type": "Deploy",
            "location": [
                3,
                5
            ],
            "name": "克洛丝",
            "direction": "Right"
        },
        {
            "type": "Deploy",
            "name": "Lancet-2",
            "direction": "Right",
            "location": [
                4,
                4
            ]
        },
        {
            "type": "Deploy",
            "name": "安赛尔",
            "location": [
                4,
                5
            ],
            "direction": "Up"
        },
        {
            "type": "Retreat",
            "name": "桃金娘",
            "location": [
                8,
                6
            ],
            "pre_delay": 200
        },
        {
            "type": "Retreat",
            "location": [
                7,
                6
            ],
            "name": "古米",
            "kills": 12
        },
        {
            "type": "Deploy",
            "name": "斑点",
            "direction": "Up",
            "location": [
                5,
                5
            ],
            "pre_delay": 300
        },
        {
            "type": "SkillDaemon"
        }
    ],
    "doc": {
        "title": "FM-7",
        "details": "——————————\n作业更新日期: 2025-07-09T07:38:06Z\n统计更新日期: 2025-07-11\n好评率：99.09%  浏览量：2569\n来源：焕彩gg  ID：62651\n——————————\nB站ID：焕彩GG 主页：https://space.bilibili.com/10123796\n本作业已开启截图增强\n求关注。"
    },
    "groups": [
        {
            "name": "元素奶",
            "opers": [
                {
                    "name": "纯烬艾雅法拉",
                    "skill": 1,
                    "skill_usage": 0
                },
                {
                    "name": "蜜莓",
                    "skill": 1,
                    "skill_usage": 0
                },
                {
                    "name": "褐果",
                    "skill": 1,
                    "skill_usage": 0
                }
            ]
        },
        {
            "name": "苏苏洛/华法林",
            "opers": [
                {
                    "name": "苏苏洛",
                    "skill": 2,
                    "skill_usage": 0
                },
                {
                    "name": "华法琳",
                    "skill": 1,
                    "skill_usage": 0
                }
            ]
        }
    ],
    "opers": [
        {
            "name": "乌尔比安",
            "skill": 2,
            "skill_usage": 0
        },
        {
            "name": "古米",
            "skill": 1,
            "skill_usage": 0
        },
        {
            "name": "斑点",
            "skill": 1,
            "skill_usage": 0
        },
        {
            "name": "安赛尔",
            "skill": 1,
            "skill_usage": 0
        },
        {
            "name": "桃金娘",
            "skill": 1,
            "skill_usage": 2,
            "skill_times": 1
        },
        {
            "name": "Lancet-2",
            "skill": 1,
            "skill_usage": 0
        },
        {
            "name": "克洛丝",
            "skill": 1,
            "skill_usage": 0
        }
    ],
    "difficulty": 3
}